betterlogs/__init__.py
betterlogs/logger.py
betterlogs-0.0.1.dist-info/METADATA
betterlogs-0.0.1.dist-info/WHEEL
betterlogs-0.0.1.dist-info/top_level.txt
betterlogs-0.0.1.dist-info/RECORD
