Metadata-Version: 2.1
Name: betterlogs
Version: 0.0.1
Summary: A improved logging system for python
Author-email: CheatBetter <vitalistrashlool@gmail.com>
Project-URL: Homepage, https://github.com/CheatBetter/BetterLogging
Project-URL: Bug Tracker, https://github.com/CheatBetter/BetterLogging/issues
Classifier: Programming Language :: Python :: 3
Classifier: License :: OSI Approved :: MIT License
Classifier: Operating System :: OS Independent
Requires-Python: >=3.7
